[{"vesselName ":"Hyundai","incomingVoyageNumber":"WAUUL98E38A037429","outgoingVoyageNumber":"JTHBP5C25A5681807","averageSpeed":68,"distanceToGo":11,"berthingTime":"3/2/2021","departureTime":"8/27/2020","berthNumber":1,"status":"true"},
{"vesselName ":"Oldsmobile","incomingVoyageNumber":"JTHBE5C2XC5565236","outgoingVoyageNumber":"KMHCT4AE8DU301048","averageSpeed":47,"distanceToGo":48,"berthingTime":"11/23/2020","departureTime":"3/16/2021","berthNumber":2,"status":"false"},
{"vesselName ":"Toyota","incomingVoyageNumber":"1G4GG5E31DF755974","outgoingVoyageNumber":"1GD312CG7CF992553","averageSpeed":39,"distanceToGo":27,"berthingTime":"1/11/2021","departureTime":"4/22/2020","berthNumber":3,"status":"false"},
{"vesselName ":"Volkswagen","incomingVoyageNumber":"JN8AE2KP3E9431970","outgoingVoyageNumber":"3VW8S7ATXFM545494","averageSpeed":42,"distanceToGo":85,"berthingTime":"12/8/2020","departureTime":"12/11/2020","berthNumber":4,"status":"true"},
{"vesselName ":"Aston Martin","incomingVoyageNumber":"NM0KS9BN3AT138399","outgoingVoyageNumber":"3N6CM0KN4FK090438","averageSpeed":42,"distanceToGo":57,"berthingTime":"8/31/2020","departureTime":"12/22/2020","berthNumber":5,"status":false},
{"vesselName ":"Lamborghini","incomingVoyageNumber":"WP0CA2A89FS613824","outgoingVoyageNumber":"WAUEG78E96A924785","averageSpeed":88,"distanceToGo":11,"berthingTime":"11/10/2020","departureTime":"5/3/2020","berthNumber":6,"status":false},
{"vesselName ":"Pontiac","incomingVoyageNumber":"WBANB33564B295024","outgoingVoyageNumber":"NM0KS6AN3AT822143","averageSpeed":6,"distanceToGo":45,"berthingTime":"3/31/2020","departureTime":"5/31/2020","berthNumber":7,"status":false},
{"vesselName ":"GMC","incomingVoyageNumber":"JH4DC43551S670168","outgoingVoyageNumber":"1N6BF0KX6FN577805","averageSpeed":39,"distanceToGo":10,"berthingTime":"12/5/2020","departureTime":"7/11/2020","berthNumber":8,"status":true},
{"vesselName ":"Aston Martin","incomingVoyageNumber":"WAUHF78PX8A531981","outgoingVoyageNumber":"1G6DF5EY9B0761997","averageSpeed":57,"distanceToGo":33,"berthingTime":"5/12/2020","departureTime":"6/3/2020","berthNumber":9,"status":true},
{"vesselName ":"Chevrolet","incomingVoyageNumber":"2C3CDXEJ3CH029802","outgoingVoyageNumber":"WP0CB2A87FS530650","averageSpeed":45,"distanceToGo":35,"berthingTime":"3/30/2020","departureTime":"5/17/2020","berthNumber":10,"status":false},
{"vesselName ":"Nissan","incomingVoyageNumber":"WBAAV33411E217662","outgoingVoyageNumber":"SAJWA4ECXCM614411","averageSpeed":82,"distanceToGo":55,"berthingTime":"10/24/2020","departureTime":"9/5/2020","berthNumber":11,"status":true},
{"vesselName ":"Volkswagen","incomingVoyageNumber":"1D4PU2GK8AW336549","outgoingVoyageNumber":"5J8TB3H30DL905271","averageSpeed":90,"distanceToGo":44,"berthingTime":"5/17/2020","departureTime":"3/23/2020","berthNumber":12,"status":true},
{"vesselName ":"Volkswagen","incomingVoyageNumber":"WA1DMAFP7FA300549","outgoingVoyageNumber":"WVGFF9BPXBD599326","averageSpeed":9,"distanceToGo":27,"berthingTime":"6/11/2020","departureTime":"11/20/2020","berthNumber":13,"status":true},
{"vesselName ":"Mazda","incomingVoyageNumber":"3GYFK66N53G689036","outgoingVoyageNumber":"1FTKR1AD0AP129786","averageSpeed":73,"distanceToGo":12,"berthingTime":"1/31/2021","departureTime":"8/20/2020","berthNumber":14,"status":false},
{"vesselName ":"Chevrolet","incomingVoyageNumber":"SCFEBBAC1AG025567","outgoingVoyageNumber":"WAUBFAFL7EN854120","averageSpeed":6,"distanceToGo":15,"berthingTime":"6/24/2020","departureTime":"5/29/2020","berthNumber":15,"status":true},
{"vesselName ":"Chevrolet","incomingVoyageNumber":"WBA3B3G55FN761996","outgoingVoyageNumber":"1GYS3BEF8ER698914","averageSpeed":65,"distanceToGo":81,"berthingTime":"11/13/2020","departureTime":"1/8/2021","berthNumber":16,"status":false},
{"vesselName ":"Audi","incomingVoyageNumber":"1GKUKFDJ9AR178881","outgoingVoyageNumber":"WVWBB7AJ5DW837378","averageSpeed":95,"distanceToGo":88,"berthingTime":"11/18/2020","departureTime":"10/4/2020","berthNumber":17,"status":true},
{"vesselName ":"BMW","incomingVoyageNumber":"JTHBK1EGXC2370085","outgoingVoyageNumber":"JTHDU5EF2C5191474","averageSpeed":38,"distanceToGo":66,"berthingTime":"12/15/2020","departureTime":"1/24/2021","berthNumber":18,"status":true},
{"vesselName ":"Cadillac","incomingVoyageNumber":"3N1CN7APXEL464817","outgoingVoyageNumber":"1GKUCKE09AR965597","averageSpeed":87,"distanceToGo":89,"berthingTime":"11/7/2020","departureTime":"12/7/2020","berthNumber":19,"status":false},
{"vesselName ":"Suzuki","incomingVoyageNumber":"WBAWL73569P512882","outgoingVoyageNumber":"YV140MAK4F1090906","averageSpeed":64,"distanceToGo":10,"berthingTime":"10/19/2020","departureTime":"5/1/2020","berthNumber":20,"status":false},
{"vesselName ":"Honda","incomingVoyageNumber":"SAJWA6FC6E8067045","outgoingVoyageNumber":"WUALNAFG5EN588127","averageSpeed":1,"distanceToGo":54,"berthingTime":"4/17/2020","departureTime":"11/20/2020","berthNumber":21,"status":false},
{"vesselName ":"Chevrolet","incomingVoyageNumber":"1FTMF1E8XAK262258","outgoingVoyageNumber":"1G6DL5E39D0659910","averageSpeed":100,"distanceToGo":90,"berthingTime":"3/21/2020","departureTime":"11/14/2020","berthNumber":22,"status":true},
{"vesselName ":"Chrysler","incomingVoyageNumber":"1D7CE3GK7AS237426","outgoingVoyageNumber":"JM1NC2SF1F0391551","averageSpeed":72,"distanceToGo":21,"berthingTime":"4/2/2020","departureTime":"12/21/2020","berthNumber":23,"status":true},
{"vesselName ":"Honda","incomingVoyageNumber":"19XFA1F34BE430414","outgoingVoyageNumber":"WA1DGAFE1DD991966","averageSpeed":92,"distanceToGo":60,"berthingTime":"4/1/2020","departureTime":"3/29/2020","berthNumber":24,"status":true},
{"vesselName ":"Audi","incomingVoyageNumber":"WBAYB6C59FD329723","outgoingVoyageNumber":"JTDZN3EU5E3943464","averageSpeed":84,"distanceToGo":11,"berthingTime":"8/11/2020","departureTime":"6/14/2020","berthNumber":25,"status":false},
{"vesselName ":"Pontiac","incomingVoyageNumber":"3D7TT2HT7BG129176","outgoingVoyageNumber":"SCFBF04B78G501149","averageSpeed":28,"distanceToGo":34,"berthingTime":"11/25/2020","departureTime":"6/24/2020","berthNumber":26,"status":true},
{"vesselName ":"GMC","incomingVoyageNumber":"4A31K2DF4BE447832","outgoingVoyageNumber":"SCBBR9ZAXBC617408","averageSpeed":15,"distanceToGo":70,"berthingTime":"9/28/2020","departureTime":"12/26/2020","berthNumber":27,"status":false},
{"vesselName ":"Honda","incomingVoyageNumber":"WBA3V7C50EJ579245","outgoingVoyageNumber":"WAU4FAFL6CA396728","averageSpeed":58,"distanceToGo":29,"berthingTime":"10/22/2020","departureTime":"1/8/2021","berthNumber":28,"status":true},
{"vesselName ":"Kia","incomingVoyageNumber":"1FMJK1JT2FE756995","outgoingVoyageNumber":"2G4WE587081850409","averageSpeed":20,"distanceToGo":70,"berthingTime":"12/12/2020","departureTime":"9/22/2020","berthNumber":29,"status":true},
{"vesselName ":"Toyota","incomingVoyageNumber":"1C4RDJDG5DC916301","outgoingVoyageNumber":"WUAUUAFG2BN845957","averageSpeed":79,"distanceToGo":18,"berthingTime":"9/28/2020","departureTime":"2/6/2021","berthNumber":30,"status":false},
{"vesselName ":"Lexus","incomingVoyageNumber":"2HNYD18653H440537","outgoingVoyageNumber":"SCFAD05D69G791645","averageSpeed":11,"distanceToGo":80,"berthingTime":"3/21/2020","departureTime":"7/18/2020","berthNumber":31,"status":true},
{"vesselName ":"Honda","incomingVoyageNumber":"SCBZB25E22C503616","outgoingVoyageNumber":"WA1LFBFP6DA038418","averageSpeed":76,"distanceToGo":88,"berthingTime":"8/13/2020","departureTime":"8/25/2020","berthNumber":32,"status":true},
{"vesselName ":"Toyota","incomingVoyageNumber":"1G4GE5G38CF420065","outgoingVoyageNumber":"YV140MAM3F1015440","averageSpeed":11,"distanceToGo":47,"berthingTime":"7/21/2020","departureTime":"4/28/2020","berthNumber":33,"status":true},
{"vesselName ":"Dodge","incomingVoyageNumber":"JN1CV6EK3FM499067","outgoingVoyageNumber":"1GKS1HE00ER772955","averageSpeed":39,"distanceToGo":94,"berthingTime":"10/22/2020","departureTime":"1/8/2021","berthNumber":34,"status":true},
{"vesselName ":"Nissan","incomingVoyageNumber":"WAUDGBFL2CA927054","outgoingVoyageNumber":"1GD02ZCG0CF010774","averageSpeed":96,"distanceToGo":30,"berthingTime":"7/12/2020","departureTime":"11/3/2020","berthNumber":35,"status":false},
{"vesselName ":"Dodge","incomingVoyageNumber":"3GYFK66N24G511750","outgoingVoyageNumber":"TRURD38J091444356","averageSpeed":82,"distanceToGo":31,"berthingTime":"12/8/2020","departureTime":"4/25/2020","berthNumber":36,"status":true},
{"vesselName ":"Lexus","incomingVoyageNumber":"WBAEA53589C801033","outgoingVoyageNumber":"5N1CR2MM3EC715268","averageSpeed":55,"distanceToGo":42,"berthingTime":"12/7/2020","departureTime":"2/28/2021","berthNumber":37,"status":false},
{"vesselName ":"Dodge","incomingVoyageNumber":"1C4RDJDG5FC967350","outgoingVoyageNumber":"WAUJT54BX3N932733","averageSpeed":60,"distanceToGo":15,"berthingTime":"3/19/2021","departureTime":"9/9/2020","berthNumber":38,"status":false},
{"vesselName ":"Land Rover","incomingVoyageNumber":"WBAFZ9C58CC714292","outgoingVoyageNumber":"1C3BC5ED1AN642647","averageSpeed":46,"distanceToGo":97,"berthingTime":"10/6/2020","departureTime":"2/21/2021","berthNumber":39,"status":false},
{"vesselName ":"Audi","incomingVoyageNumber":"WBA3B5C5XEF250052","outgoingVoyageNumber":"WBAYG0C52DD010501","averageSpeed":39,"distanceToGo":11,"berthingTime":"6/27/2020","departureTime":"6/21/2020","berthNumber":40,"status":true},
{"vesselName ":"Volvo","incomingVoyageNumber":"3D73M4EL6BG952940","outgoingVoyageNumber":"1FTEX1CM1CF542437","averageSpeed":51,"distanceToGo":97,"berthingTime":"11/9/2020","departureTime":"9/25/2020","berthNumber":41,"status":false},
{"vesselName ":"Ford","incomingVoyageNumber":"JM3TB2CA8E0339109","outgoingVoyageNumber":"SCFHDDAJ7CA304318","averageSpeed":66,"distanceToGo":13,"berthingTime":"2/12/2021","departureTime":"4/27/2020","berthNumber":42,"status":true},
{"vesselName ":"Chevrolet","incomingVoyageNumber":"1GYFK43898R943518","outgoingVoyageNumber":"WBADN53453G936378","averageSpeed":52,"distanceToGo":26,"berthingTime":"4/2/2020","departureTime":"5/26/2020","berthNumber":43,"status":true},
{"vesselName ":"Mercedes-Benz","incomingVoyageNumber":"1D7RE3BKXBS635040","outgoingVoyageNumber":"5TDBM5G18BS383663","averageSpeed":88,"distanceToGo":84,"berthingTime":"3/13/2021","departureTime":"10/5/2020","berthNumber":44,"status":true},
{"vesselName ":"Lincoln","incomingVoyageNumber":"3N1AB7AP6FL750519","outgoingVoyageNumber":"3VW217AU9FM332750","averageSpeed":69,"distanceToGo":18,"berthingTime":"7/31/2020","departureTime":"4/26/2020","berthNumber":45,"status":false},
{"vesselName ":"Infiniti","incomingVoyageNumber":"ZFF60FCA3A0743322","outgoingVoyageNumber":"1GYS4EEJ3BR461231","averageSpeed":11,"distanceToGo":21,"berthingTime":"3/25/2020","departureTime":"9/18/2020","berthNumber":46,"status":true},
{"vesselName ":"Porsche","incomingVoyageNumber":"WAU4GBFB4BN336447","outgoingVoyageNumber":"WA1WYAFE6AD839716","averageSpeed":47,"distanceToGo":41,"berthingTime":"12/6/2020","departureTime":"3/16/2021","berthNumber":47,"status":false},
{"vesselName ":"Dodge","incomingVoyageNumber":"1VWAH7A31DC806171","outgoingVoyageNumber":"JN8AE2KP3F9340344","averageSpeed":79,"distanceToGo":59,"berthingTime":"8/14/2020","departureTime":"6/19/2020","berthNumber":48,"status":false},
{"vesselName ":"Ford","incomingVoyageNumber":"19UUA9F55DA756737","outgoingVoyageNumber":"WBA3A5C53CF219838","averageSpeed":99,"distanceToGo":15,"berthingTime":"10/13/2020","departureTime":"7/5/2020","berthNumber":49,"status":true},
{"vesselName ":"Saab","incomingVoyageNumber":"JH4DC53826S527041","outgoingVoyageNumber":"3C6LD4BTXCG043624","averageSpeed":92,"distanceToGo":75,"berthingTime":"5/17/2020","departureTime":"12/24/2020","berthNumber":50,"status":true},
{"vesselName ":"Studebaker","incomingVoyageNumber":"1GKS1GKC1FR802944","outgoingVoyageNumber":"SALFP2BG8FH985825","averageSpeed":61,"distanceToGo":69,"berthingTime":"4/2/2020","departureTime":"5/26/2020","berthNumber":51,"status":true},
{"vesselName ":"Volvo","incomingVoyageNumber":"2T1BURHE0FC255263","outgoingVoyageNumber":"1FTWX3D59AE911541","averageSpeed":70,"distanceToGo":57,"berthingTime":"2/19/2021","departureTime":"4/25/2020","berthNumber":52,"status":false},
{"vesselName ":"Mazda","incomingVoyageNumber":"1FTEW1C81AF236423","outgoingVoyageNumber":"JN8AZ1MU6DW775312","averageSpeed":62,"distanceToGo":4,"berthingTime":"5/24/2020","departureTime":"2/19/2021","berthNumber":53,"status":true},
{"vesselName ":"Land Rover","incomingVoyageNumber":"WBAWL73588P179356","outgoingVoyageNumber":"3C63D3EL3CG632374","averageSpeed":86,"distanceToGo":12,"berthingTime":"11/6/2020","departureTime":"12/20/2020","berthNumber":54,"status":true},
{"vesselName ":"Volkswagen","incomingVoyageNumber":"SALSF2D4XDA486311","outgoingVoyageNumber":"JH4CU2F64BC647039","averageSpeed":84,"distanceToGo":52,"berthingTime":"2/24/2021","departureTime":"2/9/2021","berthNumber":55,"status":true},
{"vesselName ":"Dodge","incomingVoyageNumber":"WVGAV7AX0FW164828","outgoingVoyageNumber":"2G4GN5EX9F9627390","averageSpeed":84,"distanceToGo":27,"berthingTime":"12/9/2020","departureTime":"8/16/2020","berthNumber":56,"status":false},
{"vesselName ":"Aston Martin","incomingVoyageNumber":"WAUFFBFL1DN301906","outgoingVoyageNumber":"JTHDU1EF7D5488802","averageSpeed":27,"distanceToGo":40,"berthingTime":"8/23/2020","departureTime":"4/18/2020","berthNumber":57,"status":true},
{"vesselName ":"Dodge","incomingVoyageNumber":"3VW467AT8CM180179","outgoingVoyageNumber":"JH4NA21694S562019","averageSpeed":87,"distanceToGo":89,"berthingTime":"6/11/2020","departureTime":"6/8/2020","berthNumber":58,"status":true},
{"vesselName ":"Ford","incomingVoyageNumber":"3C6TD5KT4CG769825","outgoingVoyageNumber":"SCFEBBAK5CG780814","averageSpeed":69,"distanceToGo":21,"berthingTime":"9/10/2020","departureTime":"6/5/2020","berthNumber":59,"status":true},
{"vesselName ":"Suzuki","incomingVoyageNumber":"WAUSF78E47A847167","outgoingVoyageNumber":"1G4PS5SK3E4776378","averageSpeed":58,"distanceToGo":12,"berthingTime":"10/23/2020","departureTime":"5/4/2020","berthNumber":60,"status":false},
{"vesselName ":"Ford","incomingVoyageNumber":"3D7LT2ET4BG374697","outgoingVoyageNumber":"1GYS4CEF1ER564863","averageSpeed":62,"distanceToGo":16,"berthingTime":"11/19/2020","departureTime":"9/22/2020","berthNumber":61,"status":false},
{"vesselName ":"Dodge","incomingVoyageNumber":"WAUDH78E88A831364","outgoingVoyageNumber":"5N3ZA0NC3AN445699","averageSpeed":86,"distanceToGo":83,"berthingTime":"9/29/2020","departureTime":"3/7/2021","berthNumber":62,"status":false},
{"vesselName ":"Cadillac","incomingVoyageNumber":"WAUVT58E25A273384","outgoingVoyageNumber":"1G6DF8E59D0978301","averageSpeed":87,"distanceToGo":21,"berthingTime":"11/28/2020","departureTime":"8/22/2020","berthNumber":63,"status":true},
{"vesselName ":"Mercedes-Benz","incomingVoyageNumber":"5NPDH4AE9BH874476","outgoingVoyageNumber":"NM0AE8F76F1085094","averageSpeed":40,"distanceToGo":74,"berthingTime":"4/26/2020","departureTime":"2/15/2021","berthNumber":64,"status":true},
{"vesselName ":"Pontiac","incomingVoyageNumber":"KNDJT2A26D7030382","outgoingVoyageNumber":"5NPDH4AE2BH915563","averageSpeed":10,"distanceToGo":93,"berthingTime":"2/27/2021","departureTime":"6/8/2020","berthNumber":65,"status":false},
{"vesselName ":"GMC","incomingVoyageNumber":"W06VR54R41R640082","outgoingVoyageNumber":"WBAFZ9C52DD595361","averageSpeed":76,"distanceToGo":81,"berthingTime":"1/28/2021","departureTime":"7/16/2020","berthNumber":66,"status":false},
{"vesselName ":"Volvo","incomingVoyageNumber":"WVWGU7AN3CE106794","outgoingVoyageNumber":"5GAKVAED0CJ273855","averageSpeed":68,"distanceToGo":86,"berthingTime":"4/11/2020","departureTime":"3/13/2021","berthNumber":67,"status":false},
{"vesselName ":"Land Rover","incomingVoyageNumber":"2B3CA8CT8AH184360","outgoingVoyageNumber":"2B3CJ5DT8BH237136","averageSpeed":4,"distanceToGo":47,"berthingTime":"11/20/2020","departureTime":"9/12/2020","berthNumber":68,"status":false},
{"vesselName ":"Oldsmobile","incomingVoyageNumber":"5J6TF1H58EL203770","outgoingVoyageNumber":"5J8TB3H59EL037368","averageSpeed":72,"distanceToGo":97,"berthingTime":"12/1/2020","departureTime":"6/12/2020","berthNumber":69,"status":false},
{"vesselName ":"Suzuki","incomingVoyageNumber":"1FTEW1C84AK858764","outgoingVoyageNumber":"1GYS4SKJ0FR878377","averageSpeed":91,"distanceToGo":72,"berthingTime":"2/2/2021","departureTime":"1/17/2021","berthNumber":70,"status":false},
{"vesselName ":"GMC","incomingVoyageNumber":"19XFB2F50EE018970","outgoingVoyageNumber":"5UXFA93504L698504","averageSpeed":33,"distanceToGo":47,"berthingTime":"8/27/2020","departureTime":"2/7/2021","berthNumber":71,"status":false},
{"vesselName ":"Suzuki","incomingVoyageNumber":"JH4DC53016S049737","outgoingVoyageNumber":"3FADP4AJ7CM545308","averageSpeed":19,"distanceToGo":44,"berthingTime":"1/6/2021","departureTime":"5/10/2020","berthNumber":72,"status":false},
{"vesselName ":"Toyota","incomingVoyageNumber":"WVGAV7AXXCW829911","outgoingVoyageNumber":"KMHGC4DE9BU760406","averageSpeed":12,"distanceToGo":90,"berthingTime":"1/13/2021","departureTime":"4/20/2020","berthNumber":73,"status":false},
{"vesselName ":"Mitsubishi","incomingVoyageNumber":"JTDKDTB30F1185725","outgoingVoyageNumber":"2G4WF551541471171","averageSpeed":72,"distanceToGo":78,"berthingTime":"5/24/2020","departureTime":"3/17/2021","berthNumber":74,"status":true},
{"vesselName ":"GMC","incomingVoyageNumber":"WAUWFAFH5CN537477","outgoingVoyageNumber":"1G6AB5S3XD0952127","averageSpeed":87,"distanceToGo":28,"berthingTime":"10/23/2020","departureTime":"3/12/2021","berthNumber":75,"status":false},
{"vesselName ":"Ford","incomingVoyageNumber":"1G6DE5EY3B0211519","outgoingVoyageNumber":"JM3TB2BA4E0581087","averageSpeed":94,"distanceToGo":66,"berthingTime":"12/28/2020","departureTime":"7/25/2020","berthNumber":76,"status":true},
{"vesselName ":"Chevrolet","incomingVoyageNumber":"WAUKD78P87A888425","outgoingVoyageNumber":"5FRYD3H93GB865180","averageSpeed":28,"distanceToGo":37,"berthingTime":"7/24/2020","departureTime":"1/20/2021","berthNumber":77,"status":true},
{"vesselName ":"Lexus","incomingVoyageNumber":"YV1382MW8A2956200","outgoingVoyageNumber":"3GYFNFE39ES893734","averageSpeed":40,"distanceToGo":80,"berthingTime":"5/7/2020","departureTime":"1/8/2021","berthNumber":78,"status":true},
{"vesselName ":"Mitsubishi","incomingVoyageNumber":"1GT01ZCG6EF486926","outgoingVoyageNumber":"5J6TF2H56EL620195","averageSpeed":81,"distanceToGo":35,"berthingTime":"5/25/2020","departureTime":"5/29/2020","berthNumber":79,"status":true},
{"vesselName ":"Pontiac","incomingVoyageNumber":"1GYFK36229R516992","outgoingVoyageNumber":"WBAKB0C52AC944261","averageSpeed":66,"distanceToGo":2,"berthingTime":"6/24/2020","departureTime":"9/8/2020","berthNumber":80,"status":true},
{"vesselName ":"Lexus","incomingVoyageNumber":"SALAK2V60FA217762","outgoingVoyageNumber":"1GYS3BEF3ER817114","averageSpeed":73,"distanceToGo":2,"berthingTime":"5/1/2020","departureTime":"5/30/2020","berthNumber":81,"status":true},
{"vesselName ":"GMC","incomingVoyageNumber":"WVWGU7AN6CE142334","outgoingVoyageNumber":"WAUAVAFA1AN850488","averageSpeed":1,"distanceToGo":23,"berthingTime":"1/24/2021","departureTime":"6/9/2020","berthNumber":82,"status":true},
{"vesselName ":"BMW","incomingVoyageNumber":"1GYS4HEF4BR335893","outgoingVoyageNumber":"SAJWA2GT3EM678519","averageSpeed":58,"distanceToGo":16,"berthingTime":"5/26/2020","departureTime":"3/27/2020","berthNumber":83,"status":false},
{"vesselName ":"Plymouth","incomingVoyageNumber":"YV1612FH7D1274399","outgoingVoyageNumber":"1G6DS8E34D0532065","averageSpeed":9,"distanceToGo":94,"berthingTime":"1/25/2021","departureTime":"12/23/2020","berthNumber":84,"status":true},
{"vesselName ":"Mitsubishi","incomingVoyageNumber":"1VWAP7A30EC180360","outgoingVoyageNumber":"3C63DPHL2CG891876","averageSpeed":55,"distanceToGo":12,"berthingTime":"12/8/2020","departureTime":"3/2/2021","berthNumber":85,"status":true},
{"vesselName ":"Lexus","incomingVoyageNumber":"5FRYD3H46GB609233","outgoingVoyageNumber":"1G4GC5G30EF941161","averageSpeed":83,"distanceToGo":85,"berthingTime":"10/19/2020","departureTime":"12/25/2020","berthNumber":86,"status":true},
{"vesselName ":"Chevrolet","incomingVoyageNumber":"WA1LFAFP8CA976123","outgoingVoyageNumber":"5N1AR1NB6CC057974","averageSpeed":67,"distanceToGo":74,"berthingTime":"7/2/2020","departureTime":"1/17/2021","berthNumber":87,"status":false},
{"vesselName ":"Chevrolet","incomingVoyageNumber":"3G5DA03L06S641713","outgoingVoyageNumber":"5N1AR2MM6DC875036","averageSpeed":36,"distanceToGo":88,"berthingTime":"10/23/2020","departureTime":"5/1/2020","berthNumber":88,"status":false},
{"vesselName ":"Volvo","incomingVoyageNumber":"2B3CL3CG8BH498687","outgoingVoyageNumber":"1G6KD54Y74U319276","averageSpeed":47,"distanceToGo":71,"berthingTime":"5/31/2020","departureTime":"10/18/2020","berthNumber":89,"status":true},
{"vesselName ":"Mitsubishi","incomingVoyageNumber":"19XFB4F24FE109839","outgoingVoyageNumber":"WAURFAFR4AA183896","averageSpeed":57,"distanceToGo":20,"berthingTime":"7/10/2020","departureTime":"2/7/2021","berthNumber":90,"status":true},
{"vesselName ":"Chevrolet","incomingVoyageNumber":"WBABW53444P597070","outgoingVoyageNumber":"2G4GN5EX2F9195726","averageSpeed":97,"distanceToGo":91,"berthingTime":"7/21/2020","departureTime":"7/3/2020","berthNumber":91,"status":true},
{"vesselName ":"Lotus","incomingVoyageNumber":"1FT7W2A66EE331541","outgoingVoyageNumber":"WAUBFAFL8FA385709","averageSpeed":88,"distanceToGo":11,"berthingTime":"6/7/2020","departureTime":"6/3/2020","berthNumber":92,"status":true},
{"vesselName ":"Suzuki","incomingVoyageNumber":"1G4PP5SK0D4436377","outgoingVoyageNumber":"SCFEBBBK4BG189483","averageSpeed":76,"distanceToGo":92,"berthingTime":"1/16/2021","departureTime":"1/6/2021","berthNumber":93,"status":false},
{"vesselName ":"BMW","incomingVoyageNumber":"WAUDT48H16K633319","outgoingVoyageNumber":"WAUA2AFDXDN668361","averageSpeed":9,"distanceToGo":92,"berthingTime":"9/7/2020","departureTime":"7/6/2020","berthNumber":94,"status":false},
{"vesselName ":"Pontiac","incomingVoyageNumber":"5GAKVDED4CJ889799","outgoingVoyageNumber":"1G6AB5RX3E0516097","averageSpeed":10,"distanceToGo":90,"berthingTime":"7/15/2020","departureTime":"2/1/2021","berthNumber":95,"status":false},
{"vesselName ":"GMC","incomingVoyageNumber":"JTMHY7AJ2A4904227","outgoingVoyageNumber":"2C3CDXJG7EH519480","averageSpeed":55,"distanceToGo":92,"berthingTime":"4/23/2020","departureTime":"12/13/2020","berthNumber":96,"status":false},
{"vesselName ":"Acura","incomingVoyageNumber":"5N1AN0NW8EN132903","outgoingVoyageNumber":"WA1WKAFP6AA368378","averageSpeed":29,"distanceToGo":42,"berthingTime":"6/20/2020","departureTime":"4/23/2020","berthNumber":97,"status":false},
{"vesselName ":"GMC","incomingVoyageNumber":"JH4KB16547C300546","outgoingVoyageNumber":"WBXPC93447W849535","averageSpeed":8,"distanceToGo":80,"berthingTime":"5/14/2020","departureTime":"6/22/2020","berthNumber":98,"status":false},
{"vesselName ":"Toyota","incomingVoyageNumber":"3VW1K7AJXCM207136","outgoingVoyageNumber":"4JGBF2FE6AA945399","averageSpeed":96,"distanceToGo":99,"berthingTime":"5/9/2020","departureTime":"9/25/2020","berthNumber":99,"status":false},
{"vesselName ":"Ford","incomingVoyageNumber":"3VWC17AU3FM064847","outgoingVoyageNumber":"5N1AT2ML2EC219295","averageSpeed":46,"distanceToGo":64,"berthingTime":"10/23/2020","departureTime":"2/14/2021","berthNumber":100,"status":true}]